{
  "title": "File:Biology anatomy stomach with 9 abdominal region and pectoral triangle.jpg",
  "url": "https://upload.wikimedia.org/wikipedia/commons/4/4b/Biology_anatomy_stomach_with_9_abdominal_region_and_pectoral_triangle.jpg",
  "descurl": "https://commons.wikimedia.org/wiki/File:Biology_anatomy_stomach_with_9_abdominal_region_and_pectoral_triangle.jpg",
  "author": "Abhijit pulo",
  "mime": "image/jpeg",
  "size": 116999,
  "folder": "general",
  "time": "2026-02-07T14:22:08.107299",
  "License": "cc-by-4.0",
  "LicenseShortName": "CC BY 4.0",
  "Artist": "<a href=\"//commons.wikimedia.org/w/index.php?title=User:Abhijit_pulo&amp;action=edit&amp;redlink=1\" class=\"new\" title=\"User:Abhijit pulo (page does not exist)\">Abhijit pulo</a>"
}